app01/__init__.py
app01/admin.py
app01/apps.py
app01/models.py
app01/tests.py
app01/views.py
app01/migrations/__init__.py
django_to_exe/__init__.py
django_to_exe/settings.py
django_to_exe/urls.py
django_to_exe/wsgi.py
django_to_exe-0.1.1.dist-info/METADATA
django_to_exe-0.1.1.dist-info/WHEEL
django_to_exe-0.1.1.dist-info/top_level.txt
django_to_exe-0.1.1.dist-info/RECORD
