Metadata-Version: 2.1
Name: django-to-exe
Version: 0.1.1
Summary: xxxx
Home-page: UNKNOWN
License: UNKNOWN
Platform: UNKNOWN
Requires-Dist: Django ==3.2.12
